fsoperator/__init__.py
fsoperator/__main__.py
fsoperator/core/__init__.py
fsoperator/core/core.py
managed_file_system_operator-0.0.1.dist-info/LICENSE
managed_file_system_operator-0.0.1.dist-info/METADATA
managed_file_system_operator-0.0.1.dist-info/WHEEL
managed_file_system_operator-0.0.1.dist-info/top_level.txt
managed_file_system_operator-0.0.1.dist-info/RECORD
